interrail_vision/__init__.py
interrail_vision/interrail_vision.py
interrail_vision-0.1.3.dist-info/LICENSE
interrail_vision-0.1.3.dist-info/METADATA
interrail_vision-0.1.3.dist-info/WHEEL
interrail_vision-0.1.3.dist-info/top_level.txt
interrail_vision-0.1.3.dist-info/RECORD
